[{
    "ship_type": "一等驱逐舰第二代神风型",
    "name": "神风",
    "code": "1"
  },
  {
    "ship_type": "一等驱逐舰第二代神风型",
    "name": "朝风",
    "code": "2"
  }, {
    "ship_type": "一等驱逐舰睦月型",
    "name": "睦月",
    "code": "3"
  }, {
    "ship_type": "一等驱逐舰睦月型",
    "name": "如月",
    "code": "4"
  }, {
    "ship_type": "二等巡洋舰天龙型",
    "name": "天龙",
    "code": "5"
  }, {
    "ship_type": "二等巡洋舰天龙型",
    "name": "龙田",
    "code": "6"
  }, {
    "ship_type": "二等巡洋舰球磨型",
    "name": "球磨",
    "code": "7"
  },
  {
    "ship_type": "二等巡洋舰球磨型",
    "name": "多摩",
    "code": "8"
  }
]
